fsds2021/__init__.py
fsds2021/cli.py
fsds2021/datasets.py
fsds2021/fsds2021.py
fsds2021/imports.py
fsds2021/reference.py
fsds2021/stats.py
fsds2021/utils.py
fsds2021-0.1.4.dist-info/AUTHORS.rst
fsds2021-0.1.4.dist-info/LICENSE
fsds2021-0.1.4.dist-info/METADATA
fsds2021-0.1.4.dist-info/WHEEL
fsds2021-0.1.4.dist-info/entry_points.txt
fsds2021-0.1.4.dist-info/top_level.txt
fsds2021-0.1.4.dist-info/RECORD
