Metadata-Version: 2.1
Name: fsds2021
Version: 0.1.4
Summary: Revamped version of fsds
Home-page: https://github.com/jirvingphd/fsds2021
Author: James Irving
Author-email: james.irving.phd@gmail.com
License: GNU General Public License v3
Keywords: fsds2021
Platform: UNKNOWN
Classifier: Development Status :: 2 - Pre-Alpha
Classifier: Intended Audience :: Developers
Classifier: License :: OSI Approved :: GNU General Public License v3 (GPLv3)
Classifier: Natural Language :: English
Classifier: Programming Language :: Python :: 3
Classifier: Programming Language :: Python :: 3.5
Classifier: Programming Language :: Python :: 3.6
Classifier: Programming Language :: Python :: 3.7
Classifier: Programming Language :: Python :: 3.8
Requires-Python: >=3.5
Requires-Dist: Click (>=7.0)
Requires-Dist: pandas (>=1.0)
Requires-Dist: matplotlib (>=3.2.2)
Requires-Dist: scikit-learn (>=0.22)
Requires-Dist: seaborn
